constant_check_and_kill/README.MD
constant_check_and_kill/__init__.py
constant_check_and_kill/requirements.txt
constant_check_and_kill/thirdparty.json
constant_check_and_kill-0.10.dist-info/LICENSE.rst
constant_check_and_kill-0.10.dist-info/METADATA
constant_check_and_kill-0.10.dist-info/WHEEL
constant_check_and_kill-0.10.dist-info/top_level.txt
constant_check_and_kill-0.10.dist-info/RECORD
