Metadata-Version: 2.1
Name: constant-check-and-kill
Version: 0.10
Summary: Convenient and customizable solution for monitoring and terminating processes - Windows only
Home-page: https://github.com/hansalemaos/constant_check_and_kill
Author: Johannes Fischer
Author-email: aulasparticularesdealemaosp@gmail.com
License: MIT
Keywords: killing,processes
Classifier: Development Status :: 4 - Beta
Classifier: Programming Language :: Python :: 3 :: Only
Classifier: Programming Language :: Python :: 3.10
Classifier: Topic :: Software Development :: Libraries :: Python Modules
Classifier: Topic :: Utilities
License-File: LICENSE.rst
Requires-Dist: ctrlchandler
Requires-Dist: ctypes-window-info
Requires-Dist: hackyargparser
Requires-Dist: kthread
Requires-Dist: kthread-sleep
Requires-Dist: psutil
Requires-Dist: taskkill
